lhnrenamer/__init__.py
lhnrenamer/rename.py
just_rename-1.0.2.dist-info/METADATA
just_rename-1.0.2.dist-info/WHEEL
just_rename-1.0.2.dist-info/entry_points.txt
just_rename-1.0.2.dist-info/top_level.txt
just_rename-1.0.2.dist-info/zip-safe
just_rename-1.0.2.dist-info/RECORD
